clapikit/__init__.py
clapikit/cli.py
clapikit/client.py
clapikit/parser.py
clapikit-0.1.0.dist-info/METADATA
clapikit-0.1.0.dist-info/WHEEL
clapikit-0.1.0.dist-info/entry_points.txt
clapikit-0.1.0.dist-info/top_level.txt
clapikit-0.1.0.dist-info/RECORD
