Metadata-Version: 2.4
Name: clapikit
Version: 0.1.0
Summary: CLI tool for OpenAPI specifications
Author: youyo
Requires-Python: >=3.10
Requires-Dist: click>=8.0.0
Requires-Dist: pyyaml>=6.0
Requires-Dist: requests>=2.0.0
Requires-Dist: pydantic>=2.0.0
Dynamic: author
Dynamic: requires-python
